argus/__init__.py
argus/cli.py
argus/dashboard.py
argus/dashboard_old.py
argus/pricing.py
argus/storage.py
argus/watch.py
argus/integrations/__init__.py
argus/integrations/langchain.py
hundredeyes-0.1.0.dist-info/licenses/LICENSE
hundredeyes-0.1.0.dist-info/METADATA
hundredeyes-0.1.0.dist-info/WHEEL
hundredeyes-0.1.0.dist-info/entry_points.txt
hundredeyes-0.1.0.dist-info/top_level.txt
hundredeyes-0.1.0.dist-info/RECORD
