Metadata-Version: 2.4
Name: hundredeyes
Version: 0.1.0
Summary: Open Source Observability for AI Agents
Home-page: https://github.com/sh1esty1769/argus
Author: Max
Author-email: Max <maxcodesai@example.com>
License: MIT
Project-URL: Homepage, https://github.com/sh1esty1769/argus
Project-URL: Documentation, https://github.com/sh1esty1769/argus/tree/main/docs
Project-URL: Repository, https://github.com/sh1esty1769/argus
Project-URL: Issues, https://github.com/sh1esty1769/argus/issues
Keywords: ai,agents,observability,monitoring,llm,openai,anthropic
Classifier: Development Status :: 3 - Alpha
Classifier: Intended Audience :: Developers
Classifier: Topic :: Software Development :: Libraries :: Python Modules
Classifier: License :: OSI Approved :: MIT License
Classifier: Programming Language :: Python :: 3
Classifier: Programming Language :: Python :: 3.8
Classifier: Programming Language :: Python :: 3.9
Classifier: Programming Language :: Python :: 3.10
Classifier: Programming Language :: Python :: 3.11
Classifier: Programming Language :: Python :: 3.12
Requires-Python: >=3.8
License-File: LICENSE
Requires-Dist: flask>=2.0.0
Requires-Dist: sqlalchemy>=2.0.0
Requires-Dist: click>=8.0.0
Provides-Extra: dev
Requires-Dist: pytest>=7.0.0; extra == "dev"
Requires-Dist: black>=22.0.0; extra == "dev"
Requires-Dist: flake8>=4.0.0; extra == "dev"
Dynamic: author
Dynamic: home-page
Dynamic: license-file
Dynamic: requires-python
